memocell/__init__.py
memocell/data.py
memocell/estimation.py
memocell/network.py
memocell/plots.py
memocell/selection.py
memocell/simulation.py
memocell/utils.py
memocell/simulation_lib/__init__.py
memocell/simulation_lib/sim_gillespie.py
memocell/simulation_lib/sim_moments.py
memocell-0.1.5.dist-info/LICENSE
memocell-0.1.5.dist-info/METADATA
memocell-0.1.5.dist-info/WHEEL
memocell-0.1.5.dist-info/top_level.txt
memocell-0.1.5.dist-info/RECORD
